{
    "students":[
        {"id":1,"name":"Asmaa","age":23,"email":"asmaa@gmail.com"},
        {"id":2,"name":"mohamed","age":24,"email":"mohamed@gmail.com"},
        {"id":3,"name":"Ali","age":25,"email":"Ali@gmail.com"},
        {"id":4,"name":"aya","age":30,"email":"aya@gmail.com"},
        {"id":5,"name":"Omar","age":12,"email":"Omar@gmail.com"},
        {"id":6,"name":"Ahmed","age":20,"email":"Ahmed@gmail.com"},
        {"id":7,"name":"Dina","age":32,"email":"Dina@gmail.com"},
        {"id":8,"name":"yara","age":29,"email":"yara@gmail.com"}
    ]
}